{
  "created": "2026-06-28T02:31:04.000Z",
  "creator": {
    "email": "myhanno-bot@city-tecoli.iam.gserviceaccount.com"
  },
  "description": "2025年最後の活動は、飯能市道路美化活動団体として整備を行っている里山道で、忘年ライドを行います。\n落枝等を片付けながら里山道をツーリングします。\nみなさまのご参加をお待ちしております。\n\n■集合日時：12月21日（日）8:30\n\n■集合場所：あいわ広場（お車の駐車が可能です）\n\n【注意事項】\n●各自で水分補給やおやつの準備をお願いします。\n●前日17時の気象庁発表による埼玉県南部の天気予報で、当日6時～12時の降水確率が50％以上の場合は活動を中止といたします。\n\n📣 お知らせ: https://okumusashimtb.wixsite.com/omcweb/post/12-21忘年ライドのお知らせ\n📝 報告: https://okumusashimtb.wixsite.com/omcweb/post/12月21日（日）の活動報告",
  "end": {
    "date": "2025-12-22"
  },
  "etag": "\"3569212851902622\"",
  "eventType": "default",
  "htmlLink": "https://www.google.com/calendar/event?eid=X2R0bW02YjlpNjBwM2FiOWg2OG1qNGNhMGR0bG5hcmJsZWRnbjZxMzk1bG1uOG9nIG9rdW11c2FzaGkubXRiQG0",
  "iCalUID": "omc-2025-12-21@okumusashi-mtb",
  "id": "_dtmm6b9i60p3ab9h68mj4ca0dtlnarbledgn6q395lmn8og",
  "kind": "calendar#event",
  "organizer": {
    "email": "okumusashi.mtb@gmail.com",
    "self": true
  },
  "reminders": {
    "useDefault": false
  },
  "sequence": 0,
  "start": {
    "date": "2025-12-21"
  },
  "status": "confirmed",
  "summary": "忘年ライド",
  "updated": "2026-07-21T04:00:25.951Z"
}